pygeometa/__init__.py
pygeometa/cli_options.py
pygeometa/core.py
pygeometa/helpers.py
pygeometa/pygeoapi_plugin.py
pygeometa/schemas/__init__.py
pygeometa/schemas/base.py
pygeometa/schemas/common/iso19139-charstring.j2
pygeometa/schemas/cwl/__init__.py
pygeometa/schemas/dcat/__init__.py
pygeometa/schemas/iso19139/__init__.py
pygeometa/schemas/iso19139/contact.j2
pygeometa/schemas/iso19139/main.j2
pygeometa/schemas/iso19139_2/__init__.py
pygeometa/schemas/iso19139_2/contact.j2
pygeometa/schemas/iso19139_2/main.j2
pygeometa/schemas/iso19139_hnap/__init__.py
pygeometa/schemas/iso19139_hnap/charstring.j2
pygeometa/schemas/iso19139_hnap/contact.j2
pygeometa/schemas/iso19139_hnap/main.j2
pygeometa/schemas/mcf/core.yaml
pygeometa/schemas/mcf/iso19139_2.yaml
pygeometa/schemas/mcf/wmo-cmp.yaml
pygeometa/schemas/mcf/wmo-wcmp2.yaml
pygeometa/schemas/mcf/wmo-wigos.yaml
pygeometa/schemas/ogcapi_records/__init__.py
pygeometa/schemas/schema_org/__init__.py
pygeometa/schemas/stac/__init__.py
pygeometa/schemas/wmo_cmp/__init__.py
pygeometa/schemas/wmo_cmp/contact.j2
pygeometa/schemas/wmo_cmp/main.j2
pygeometa/schemas/wmo_wcmp2/__init__.py
pygeometa/schemas/wmo_wigos/__init__.py
pygeometa/schemas/wmo_wigos/contact.j2
pygeometa/schemas/wmo_wigos/main.j2
pygeometa-0.19.0.dist-info/licenses/LICENSE.md
pygeometa-0.19.0.dist-info/METADATA
pygeometa-0.19.0.dist-info/WHEEL
pygeometa-0.19.0.dist-info/entry_points.txt
pygeometa-0.19.0.dist-info/top_level.txt
pygeometa-0.19.0.dist-info/RECORD
