Metadata-Version: 2.4
Name: pygeometa
Version: 0.19.0
Summary: pygeometa is a Python package to manage metadata for geospatial datasets
Home-page: https://geopython.github.io/pygeometa
Author: Tom Kralidis
Author-email: tomkralidis@gmail.com
Maintainer: Tom Kralidis
Maintainer-email: tomkralidis@gmail.com
License: MIT
Keywords: geospatial metadata catalogue discovery
Platform: all
Classifier: Development Status :: 4 - Beta
Classifier: Environment :: Console
Classifier: Intended Audience :: Developers
Classifier: Intended Audience :: Science/Research
Classifier: Operating System :: OS Independent
Classifier: Programming Language :: Python
Classifier: Topic :: Scientific/Engineering :: GIS
License-File: LICENSE.md
Requires-Dist: Click
Requires-Dist: Jinja2
Requires-Dist: jsonschema
Requires-Dist: lxml
Requires-Dist: OWSLib
Requires-Dist: pyyaml
Dynamic: author
Dynamic: author-email
Dynamic: classifier
Dynamic: description
Dynamic: description-content-type
Dynamic: home-page
Dynamic: keywords
Dynamic: license
Dynamic: license-file
Dynamic: maintainer
Dynamic: maintainer-email
Dynamic: platform
Dynamic: requires-dist
Dynamic: summary
